dget/__init__.py
dget/__main__.py
dget/adduct.py
dget/convolve.py
dget/dget.py
dget/formula.py
dget/plot.py
dget/gui/__main__.py
dget/gui/colors.py
dget/gui/graphs.py
dget/gui/importdialog.py
dget/gui/log.py
dget/gui/mainwindow.py
dget/gui/npqt.py
dget/gui/report.py
dget/gui/settings.py
dget/gui/validators.py
dget/gui/docks/__init__.py
dget/gui/docks/controls.py
dget/gui/docks/results.py
dget/gui/resources/__init__.py
dget/gui/resources/icons.py
dget/io/__init__.py
dget/io/shimadzu.py
dget/io/text.py
dget-1.0.2.dist-info/licenses/LICENSE
dget-1.0.2.dist-info/METADATA
dget-1.0.2.dist-info/WHEEL
dget-1.0.2.dist-info/entry_points.txt
dget-1.0.2.dist-info/top_level.txt
dget-1.0.2.dist-info/RECORD
