Metadata-Version: 2.4
Name: DGet
Version: 1.0.2
Summary: Calculates compound deuteration from ToF-MS data.
Author-email: Thomas Lockwood <thomas.lockwood@uts.edu.au>
License-Expression: GPL-3.0-or-later
Project-URL: Homepage, https://dget.app
Project-URL: Repository, https://gtihub.com/djdt/dget
Project-URL: Documentation, https://dget.readthedocs.io
Requires-Python: >=3.9
License-File: LICENSE
Requires-Dist: numpy>=2.0
Requires-Dist: molmass
Provides-Extra: test
Requires-Dist: pytest; extra == "test"
Provides-Extra: gui
Requires-Dist: PySide6!=6.9.1; extra == "gui"
Requires-Dist: pyqtgraph; extra == "gui"
Dynamic: license-file
